sigdoc/__init__.py
sigdoc/py.typed
sigdoc-0.0.2.dist-info/LICENSE
sigdoc-0.0.2.dist-info/WHEEL
sigdoc-0.0.2.dist-info/METADATA
sigdoc-0.0.2.dist-info/RECORD
