Metadata-Version: 2.1
Name: sigdoc
Version: 0.0.2
Summary: Inline documentation of parameters, returns, and raises
Home-page: https://github.com/JacobHayes/sigdoc
License: MIT
Author: Jacob Hayes
Author-email: jacob.r.hayes@gmail.com
Requires-Python: >=3.9
Classifier: License :: OSI Approved :: MIT License
Classifier: Programming Language :: Python :: 3
Classifier: Programming Language :: Python :: 3.9
Classifier: Programming Language :: Python :: 3.10
Classifier: Programming Language :: Python :: 3.11
Project-URL: Repository, https://github.com/JacobHayes/sigdoc
